{" Travis W. Childers": 15, " Robert G. Torricelli": 66, " Robert \"Rob\" S. Walker": 154, " John E. Peterson": 124, " Danny Davis": 387, " Steve Israel": 102, " Zachary \"Zack\" T. Space": 19, " Wes Cooley": 38, " Anibal Acevedo-Vila": 13, " J. \"Randy\" Randy Forbes": 6, " Thomas \"Tom\" Davis": 232, " James Lightfoot": 31, " Richard B. Nugent": 22, " Joe Baca": 155, " Daniel P. Coughlin": 8, " Randy Neugebauer": 94, " Ken Calvert": 133, " Michael \"Mike\" D. Rogers": 31, " Wayne Allard": 72, " Frank Tejeda": 5, " Leslie Byrne": 22, " Mark Steven Kirk": 210, " John Salazar": 56, " John Ensign": 44, " Bruce Braley": 60, " Pat Roberts": 68, " Chris Bell": 20, " Todd Tiahrt": 322, " Daniel \"Dan\" J. M.D. Benishek": 8, " Thomas \"Tom\" Sawyer": 62, " Steve Largent": 54, " Virginia Foxx": 359, " Collin Peterson": 93, " Tammy Baldwin": 95, " Lane Evans": 86, " Andy Harris": 15, " John \"Russ\" Carnahan": 99, " William \"Bill\" Blaine Richardson": 166, " Raul R. Labrador": 6, " Blake Randolph Farenthold": 10, " Steve Stivers": 7, " Josiah \"Jo\" Bonner": 32, " Karan English": 3, " Shelley Sekula": 6, " James Barcia": 52, " Janice \"Jan\" Schakowsky": 248, " Howard \"Buck\" McKeon": 171, " Charles Canady": 90, " Ann Kirkpatrick": 33, " Bill Martini": 34, " Robert \"Bob\" Wise": 222, " Michael \"Mike\" Honda": 65, " Marge Roukema": 149, " Nancy Pelosi": 594, " Greg Walden": 120, " Yvette D. Clarke": 42, " Jeff Miller": 52, " Barney Frank": 482, " Charles \"Charlie\" Norwood": 154, " Earl Hilliard": 67, " Betty McCollum": 72, " Tobias \"Toby\" A. Roth": 140, " Frank C. Guinta": 11, " Philip Sharp": 13, " William \"Bill\" Sr. Clay": 85, " Aaron Jon Schock": 29, " Thomas \"Tom\" Ridge": 5, " Marcia Fudge": 32, " James Nussle": 66, " James Vear Hansen": 158, " John R. Kasich": 116, " Patrick Kennedy": 161, " Julia Carson": 104, " Samuel \"Sam\" Gejdenson": 152, " Donna F. Edwards": 94, " Ronald \"Ron\" C. Packard": 79, " Charles E. Schumer": 124, " Martin \"Marty\" Meehan": 138, " Richard \"Dick\" J. Durbin": 146, " Eugene \"Gene\" Taylor": 205, " Tim Huelskamp": 9, " Thomas J. Manton": 40, " William \"Mac\" Thornberry": 84, " Stephanie Herseth-Sandlin": 18, " Bill Redmond": 4, " Van Hilleary": 30, " Thomas \"Cass\" Cass Ballenger": 306, " Romano L. Mazzoli": 45, " William \"steve\" Steve II Southerland": 11, " Dick Chrysler": 48, " Mick Mulvaney": 9, " Eva Clayton": 321, " Steve Womack": 21, " Melissa A. Hart": 67, " Rick Lazio": 108, " Christopher \"Chris\" John": 22, " Adam Putnam": 85, " Anthony Weiner": 124, " Bob Ney": 106, " Scott Baesler": 14, " Andrew Jr. Jacobs": 23, " Steve Chabot": 332, " Dean A. Gallo": 4, " Lee Terry": 132, " Pat Toomey": 52, " Bill Paxon": 43, " Isaac \"Ike\" Skelton": 262, " David N. Cicilline": 44, " Michael \"Mike\" Quigley": 77, " David Levy": 12, " Heather Wilson": 88, " Tom Udall": 99, " David Smith Monson": 1, " Timothy \"Tim\" Murphy": 156, " Robert \"Bud\" Cramer": 47, " Samuel \"Sam\" Johnson": 352, " Spencer Bachus": 180, " Michael \"Mike\" A. Ross": 68, " Henry \"Hank\" C. Jr. Johnson": 71, " Lynn Woolsey": 667, " Thomas Barrett": 102, " Maxine Waters": 359, " Michael Grimm": 5, " William \"Bill\" F. Goodling": 183, " Daniel Lipinski": 62, " John Cooksey": 20, " Dave McCurdy": 14, " Vince Snowbarger": 13, " Rob Portman": 152, " Richard \"Dick\" N. Swett": 27, " George Miller": 552, " Cynthia McKinney": 175, " Arthur Jr. Ravenel": 8, " Bob Carr": 6, " Charles W. Stenholm": 247, " Donald Payne": 181, " Glenn \"G.T.\" Thompson": 111, " Jill Long": 8, " Gabrielle Giffords": 61, " Michael McNulty": 129, " Kathleen \"Kathy\" A. Dahlkemper": 60, " Jason Chaffetz": 48, " Kathleen \"Kathy\" Hochul": 16, " Bill Luther": 37, " J.D. Hayworth": 375, " Thomas \"Tom\" J. Rooney": 25, " Harry Teague": 25, " James Kolbe": 199, " Colleen Wakako Hanabusa": 19, " Scott Eugene Desjarlais": 1, " John W. Olver": 219, " Charles \"Chip\" W. Jr. Pickering": 49, " Anthony Beilenson": 100, " Peter Barca": 30, " Douglas Applegate": 16, " Erik Paulsen": 62, " Suzanne Bonamici": 10, " William \"Bill\" Sali": 19, " Esteban Torres": 46, " George P. Radanovich": 78, " Eric Cantor": 185, " Bart Gordon": 85, " Scott Garrett": 164, " William Janklow": 1, " Christopher Lee": 30, " Dan Frisa": 14, " Robert Dold": 32, " Peter \"Pete\" J. Visclosky": 142, " Karen Shepherd": 17, " John T. Doolittle": 146, " Jack Metcalf": 148, " Curt Weldon": 219, " Joseph \"Joe\" D. Courtney": 75, " Peter Hoekstra": 225, " W. \"W.R.\" Reynolds Jr. Archer": 104, " Lawrence \"Larry\" Kissell": 14, " Michael \"Mike\" Crapo": 44, " Walter \"Wally\" Herger": 251, " Douglas \"Mike\" McIntyre": 55, " Robert \"Rob\" R. Simmons": 38, " Glenn Nye": 21, " Edward \"Ed\" Royce": 218, " Robert Hurt": 6, " Paul Gosar": 17, " Ben Ray Lujan": 32, " James \"Jim\" Hayes Shofner Cooper": 59, " Jack Quinn": 70, " Michael Arcuri": 88, " John Tierney": 155, " Daniel \"Dan\" E. Lungren": 170, " Eric D. Fingerhut": 33, " Steven \"Steve\" King": 248, " Sandra \"Sandy\" Adams": 8, " John Carney": 16, " Bruce F. Vento": 191, " Ralph M. Hall": 128, " David Davis": 22, " Cory Gardner": 25, " Doug Ose": 65, " Todd Christopher Young": 10, " Mark R. Kennedy": 63, " Albert \"Ben\" Chandler": 18, " Gregg Harper": 16, " Randy Hultgren": 28, " Mike Parker": 23, " Fortney \"Pete\" Stark": 130, " John Jr. Conyers": 307, " Laura Richardson": 48, " Ileana Ros-Lehtinen": 459, " Lois Capps": 277, " Justin Amash": 5, " James M. Inhofe": 11, " Alan Nunnelee": 22, " Robert \"Rob\" J. Wittman": 44, " Blanche Lambert": 11, " Peter \"Pete\" Sessions": 230, " Michael Kopetski": 24, " Dave Weldon": 289, " Alan Wheat": 6, " Alcee L. Hastings": 282, " Paul E. Kanjorski": 87, " Thomas J. Jr. Bliley": 111, " Allen B. West": 14, " Eugene \"Gene\" F. Hemrick": 1, " Dave \"David\" Loebsack": 41, " Betsy Markey": 20, " Michael \"Mike\" McMahon": 23, " John \"Pat\" Patrick Williams": 87, " Ken Bentsen": 188, " Paul Hodes": 53, " Trent Franks": 80, " Donald \"Don\" Young": 188, " W. \"Bill\" G. Hefner": 87, " John Edward Porter": 121, " William R. Keating": 7, " Michael \"Mike\" Pappas": 54, " Doris O. Matsui": 125, " James \"Jim\" Marshall": 30, " Scott L. Klug": 50, " Kenny Hulshof": 73, " J. Gresham Barrett": 88, " John Tanner": 132, " Henry E. Jr. Brown": 51, " Donald \"Don\" A. Manzullo": 187, " Trey Gowdy": 10, " Samuel \"Sam\" Brownback": 42, " Bill Barrett": 98, " Charles \"Chuck\" Taylor": 50, " James Ramstad": 123, " William \"Bill\" L. Jenkins": 10, " Melissa Bean": 45, " Daniel \"Dan\" Maffei": 18, " Howard L. Berman": 176, " Jay Dickey": 68, " Joseph Crowley": 198, " Thomas \"Tom\" F. Lewis": 7, " James \"Jimmy\" Allison Hayes": 24, " Bob Livingston": 171, " Jon Porter": 44, " Gary Ackerman": 84, " Bill Baker": 64, " Mel Reynolds": 4, " Robert \"Bob\" Inglis": 74, " Bobby Schilling": 10, " Thomas Osborne": 114, " Judy Chu": 66, " Robert \"Robin\" Hayes": 127, " Thomas Foglietta": 52, " Clay \"Eugene\" E. Jr. Shaw": 166, " Edward J. Markey": 304, " William \"Bill\" M. Thomas": 243, " Tom McClintock": 67, " Michael \"Mike\" Rogers": 79, " Jim \"James\" B. Renacci": 1, " Rodney Frelinghuysen": 137, " Victor \"Vic\" Herbert Fazio": 164, " H. \"Morgan\" Morgan Griffith": 9, " John Garamendi": 60, " Elijah Cummings": 228, " Terrycina \"Terri\" Andrea Sewell": 15, " Butler Derrick": 52, " Stephen \"Steve\" Fincher": 5, " Ernest Jim Istook": 96, " John James Jr. Duncan": 366, " Byron P. Brought": 1, " Robert Underwood": 184, " Clyde Mighells": 1, " Michael \"Mike\" Ferguson": 41, " Douglas \"Doug\" L. Lamborn": 55, " Janice K Hahn": 12, " John E. Linder": 286, " Dennis Cardoza": 83, " John Campbell": 64, " L. Diaz-Balart": 316, " Larry LaRocco": 17, " John \"Howard\" Coble": 190, " Dennis Moore": 63, " James Turner": 120, " George J. Hochbrueckner": 6, " Earl Blumenauer": 585, " Jim Ryun": 89, " Rod Blagojevich": 49, " Ruben Hinojosa": 143, " Martin Heinrich": 37, " Larry D. Bucshon": 11, " Robert H. Michel": 42, " Bobby Bright": 17, " Tim Scott": 15, " Robert \"Bob\" Borski": 52, " George \"Buddy\" Darden": 10, " David M. McIntosh": 101, " Rick Larsen": 48, " Mac Collins": 101, " Debbie Wasserman Schultz": 142, " Steve Stockman": 16, " Zoe Lofgren": 188, " James B. Jr. Longley": 48, " Stephanie Herseth": 29, " L. \"L.F.\" F. Jr. Payne": 42, " George E. Jr. Brown": 100, " David Funderburk": 70, " Steven \"Steve\" L. Driehaus": 27, " Linda T. Sanchez": 77, " Gary Condit": 58, " Michael \"Mike\" Michaud": 81, " Virginia \"Ginny\" Brown-Waite": 141, " Nancy Boyda": 23, " Barbara Cubin": 69, " Charles Wilson": 16, " Luis Gutierrez": 138, " William \"Bill\" D. Delahunt": 133, " Albio Sires": 97, " John M Jr. Spratt": 209, " Linda Smith": 77, " Frank R. Wolf": 350, " Jeb Hensarling": 187, " Ron De Lugo": 16, " Chellie Pingree": 48, " Harold E. Jr. Ford": 70, " Baron Hill": 56, " Nathan Deal": 120, " Brian Baird": 114, " Neil Abercrombie": 196, " Michael \"Mike\" F. Doyle": 77, " Kurt Schrader": 22, " James \"Jim\" David Matheson": 73, " H. \"James\" James Saxton": 201, " Floyd H. Flake": 54, " Phil Hare": 73, " Ra\u00fal Grijalva": 61, " Richard Neal": 194, " Joe Walsh": 3, " James Lankford": 26, " Jay Kim": 74, " Mike Kelly": 10, " Pete Olson": 64, " Christopher \"Chris\" B. Cannon": 77, " William Jr. Clinger": 99, " Jon Kyl": 18, " James \"Jim\" Moran": 463, " John P. Sarbanes": 66, " Merrill Cook": 47, " Rick Crawford": 19, " Carol Shea-Porter": 77, " Floyd D. Spence": 74, " Glenn Poshard": 37, " Darlene Hooley": 137, " James H. Maloney": 22, " Anne Meagher Northup": 51, " Keith Ellison": 136, " Donald \"Don\" K. Sundquist": 2, " Don Edwards": 19, " David R. Obey": 505, " Herbert Klein": 17, " David \"Dan\" Boren": 45, " Steve Gunderson": 51, " Stephen F. Lynch": 76, " Nita Lowey": 289, " Patrick J. Conroy": 4, " Matthew G. Martinez": 75, " George Sangmeister": 11, " Gil Gutknecht": 268, " Marsha Blackburn": 269, " Phil English": 163, " James Talent": 73, " Paul Ryan": 159, " Preston \"Pete\" M. III Geren": 32, " Thomas Ewing": 162, " Ted Strickland": 125, " Gerald \"Gerry\" E. Connolly": 24, " Xavier Becerra": 202, " Suzan DelBene": 1, " Lucien Blackwell": 6, " Charles Bass": 96, " Bill Sarpalius": 11, " Ernest \"Ernie\" Fletcher": 47, " Glen Browder": 36, " Tim Holden": 63, " Nancy Johnson": 230, " Michael E Sodrel": 10, " Cedric L Richmond": 6, " Michael Forbes": 76, " Steven R. Rothman": 87, " Bennie Thompson": 77, " Roscoe Bartlett": 308, " Robert Menendez": 244, " Tim Griffin": 12, " Carolyn McCarthy": 139, " John Carter": 92, " Thomas Massie": 1, " Roger Wicker": 103, " Geoffrey \"Geoff\" C. Davis": 64, " Allen Boyd": 76, " John N. Hostettler": 73, " Jaime Herrera": 8, " G. \"Sonny\" V. Montgomery": 108, " Louis \"Louie\" B. Jr. Gohmert": 236, " Christopher \"Chris\" P. Carney": 20, " Frank A. LoBiondo": 72, " John Calvin Jr. Fleming": 87, " Zachary \"Zach\" Wamp": 146, " Charles \"Charlie\" Wilson": 51, " Lincoln Davis": 37, " Charles \"Charlie\" A. Gonzalez": 47, " John Lewis": 329, " Elizabeth Furse": 154, " William \"Bill\" Shuster": 82, " John Boccieri": 36, " Harry A. Johnston": 36, " Michael \"Mike\" G Fitzpatrick": 43, " Lynn A. Westmoreland": 125, " Sherwood L. Boehlert": 207, " David Mann": 2, " Martin Hoke": 186, " Jim Gerlach": 16, " Duncan Lee Hunter": 286, " Ric Keller": 89, " Alice \"Dina\" Titus": 48, " Norman Y. Mineta": 67, " Thomas \"Tom\" Price": 260, " William \"Bill\" J. Jr. Pascrell": 245, " Ellen O. Tauscher": 98, " Joseph \"Joe\" A. Jr. Sestak": 58, " Tim Roemer": 247, " Mark Amodei": 3, " Jesse Jr. Jackson": 98, " Charles \"Charlie\" Dent": 74, " Jim Bunning": 68, " Lindsey Graham": 74, " Bill Posey": 13, " Lynn Jenkins": 35, " Lynn Schenk": 30, " Gus Michael Bilirakis": 46, " Shelley Moore Capito": 162, " David \"Dave\" Reichert": 72, " Brad Sherman": 162, " Eric Massa": 8, " Bart Stupak": 316, " Diana L. DeGette": 107, " Thomas \"Tom\" H. Allen": 185, " Austin Scott": 8, " Sherrod Brown": 382, " James \"Jim\" McDermott": 410, " Daniel \"Dan\" Schaefer": 66, " Ann Marie Buerkle": 13, " Edolphus Towns": 99, " Adam Kinzinger": 19, " James E. Clyburn": 117, " Robert \"Bob\" L. Turner": 3, " David \"Dave\" Hobson": 71, " Madeleine Bordallo": 77, " Bill Jr. McCollum": 149, " David Dreier": 681, " Helen Delich Bentley": 40, " Robert \"Bob\" Schaffer": 154, " Steven Schiff": 81, " James \"Jim\" Langevin": 154, " Dean Heller": 24, " Richard H. Lehman": 21, " Douglas \"Pete\" B. Peterson": 42, " David \"Phil\" P. Roe": 58, " Thomas \"Tom\" Petri": 133, " Timothy \"Tim\" H. Bishop": 89, " Felix Jr. Grucci": 21, " John \"Randy\" Jr. Kuhl": 26, " Melton \"Mel\" Hancock": 22, " Ron Klein": 92, " Joseph \"Joe\" Donnelly": 38, " Kevin McCarthy": 34, " Robert T. Aderholt": 78, " Randy Tate": 40, " Louis Stokes": 67, " Scott Tipton": 8, " Henry Waxman": 246, " Jeff Duncan": 27, " Allyson Schwartz": 100, " Cleo Fields": 53, " Bud Shuster": 98, " Victor \"Vic\" Snyder": 104, " Michael R. Turner": 53, " Butch Otter": 36, " John T. Myers": 33, " Gary G. Miller": 86, " Steny H. Hoyer": 800, " Bob Beauprez": 29, " Peter Deutsch": 108, " Addison \"Joe\" Graves Wilson": 489, " Charles B. Rangel": 280, " David Rivera": 6, " William Lacy Jr. Clay": 52, " Dan Miller": 135, " Lee H. Hamilton": 92, " Jim McCrery": 103, " W. \"Billy\" J. II Tauzin": 171, " Patsy Mink": 138, " Peter A. DeFazio": 556, " Henry Bonilla": 79, " James H. Quillen": 55, " Mark Schauer": 22, " Joseph M. McDade": 27, " Kristi Lynn Noem": 14, " Fred Grandy": 5, " John Baldacci": 96, " Candice Miller": 137, " Pedro R. Pierluisi": 22, " Robert Weygand": 39, " Solomon P. Ortiz": 76, " James L. Oberstar": 293, " Bob Franks": 38, " Mary Bono Mack": 6, " Nick Smith": 338, " Steven \"Brett\" Guthrie": 19, " Frederick \"Rick\" C. Boucher": 73, " Victor Frazer": 7, " Steven Wishart": 1, " Henry J. Hyde": 221, " Michael Garver Oxley": 151, " Frank Jr. Kratovil": 16, " Paul C. Jr. Broun": 104, " John Barrow": 51, " James \"Jim\" DeMint": 53, " Jeb Bradley": 34, " Dennis \"Denny\" Rehberg": 63, " Peter Roskam": 78, " Porter J. Goss": 449, " Rosa DeLauro": 688, " Albert Wynn": 217, " Rob Woodall": 38, " Lucille Roybal-Allard": 91, " Francis \"Frank\" X. McCloskey": 30, " Michael Capuano": 51, " Donald J. Jr. Cazayoux": 3, " C. \"Bill\" W. Young": 212, " John P. Jr. Murtha": 92, " Louis \"Lou\" J Barletta": 10, " Cardiss Collins": 67, " Ander Crenshaw": 36, " Walter Minnick": 9, " Roy Blunt": 256, " Jack Brooks": 30, " Marjorie Margolies-Mezvinsky": 10, " William Natcher": 3, " Joe Skeen": 61, " William \"Bill\" Lewis Owens": 14, " Patricia S. Schroeder": 295, " Tim Hutchinson": 73, " Carolyn Maloney": 483, " Judy Biggert": 225, " Edward L. Schrock": 15, " Denise Majette": 9, " Cathy McMorris Rodgers": 41, " Asa Hutchinson": 80, " Jerry Costello": 57, " John A. Boehner": 361, " Kirsten E. Gillibrand": 9, " Elton Gallegly": 52, " Thomas \"Tom\" Lantos": 163, " Dan Glickman": 28, " Ed Bryant": 72, " Thomas Andrews": 16, " Al Swift": 17, " Deborah Pryce": 213, " William J. Jefferson": 63, " John Hall": 79, " Frank D. Lucas": 85, " Theodore \"Todd\" Rokita": 13, " Adam B. Schiff": 160, " Jane Harman": 197, " Mark Udall": 78, " Max Sandlin": 53, " Tony P. Hall": 158, " Anh \"Joseph\" Cao": 44, " Jim Bunn": 28, " Vito Fossella": 96, " Joseph P. II Kennedy": 120, " Anna G. Eshoo": 198, " Kenny Marchant": 13, " Jon Christensen": 73, " Jack M. Fields": 48, " Ron Lewis": 109, " Richard Santorum": 9, " James \"Jim\" D. Jordan": 61, " Ken Lucas": 12, " James \"Jim\" Leach": 125, " Jim Costa": 76, " Bob Latta": 36, " Ed Pastor": 64, " Katherine Harris": 33, " Jolene Unsoeld": 37, " Stephen \"Steve\" Scalise": 77, " David E. Price": 171, " Danny \"Dan\" Lee Burton": 373, " Jamie Whitten": 1, " Rahm Emanuel": 224, " Rod Grams": 41, " Bill Huizenga": 7, " Joe Scarborough": 129, " Steven C. LaTourette": 131, " Thomas \"Tom\" Perriello": 30, " Thomas \"Chet\" Chester Edwards": 223, " William \"Bill\" O. Lipinski": 74, " Jo Ann Davis": 56, " Mary Fallin": 36, " Tom Cole": 74, " Karen Bass": 8, " Newton \"Newt\" Leroy Gingrich": 134, " Joseph \"Joe\" Pitts": 559, " Patrick Riffle": 1, " Ralph Regula": 152, " Peter Torkildsen": 76, " Joe Moakley": 212, " Harry Reid": 1, " Cynthia Lummis": 35, " Barbara F. Vucanovich": 65, " Pat Danner": 27, " Austin Murphy": 3, " Alan M. Grayson": 24, " Jared Polis": 97, " Brad Carson": 11, " Bobby Jindal": 25, " Diane Watson": 198, " Scott Murphy": 17, " Dana Rohrabacher": 385, " Helen Chenoweth": 102, " Leonard Lance": 35, " Greg Laughlin": 31, " Susan Molinari": 49, " Jeannette \"Jean\" Marie Schmidt": 70, " Richard \"Dick\" Zimmer": 60, " William \"Bill\" Flores": 16, " Bill Brewster": 25, " Robert \"Bob\" Filner": 269, " Gwendolynne \"Gwen\" Moore": 72, " Jeff Denham": 15, " Dennis Hastert": 137, " Jonas \"Martin\" Martin Frost": 241, " James Gibbons": 417, " Duncan D. Hunter": 18, " Norman \"Norm\" Dicks": 186, " Bill Orton": 56, " Michael Burgess": 199, " Dan Webster": 10, " Connie IV Mack": 22, " Reid Ribble": 3, " Timothy \"Tim\" Ryan": 147, " Eleanor Holmes Norton": 444, " John Shadegg": 155, " Melvin Watt": 264, " Walter B. Jr. Jones": 374, " Silvestre Reyes": 163, " Gerald \"Jerry\" C. Weller": 251, " Frank R. Mascara": 39, " Craig Washington": 6, " Eliot Engel": 328, " Renee Ellmers": 12, " Corrine Brown": 230, " Lloyd Doggett": 447, " Benjamin Arthur Gilman": 363, " Joel Hefley": 317, " Richard \"Dick\" K. Armey": 339, " Tim Valentine": 12, " Loretta Sanchez": 249, " Michael Wilker": 1, " Jack Kingston": 522, " Bobby Rush": 118, " David Phelps": 23, " Patrick L. Meehan": 11, " Tom Feeney": 48, " Marcia \"Marcy\" Kaptur": 470, " Mark Edward Souder": 221, " Sander Martin Levin": 324, " Suzanne Kosmas": 11, " Rick Hill": 72, " Olympia J. Snowe": 11, " Robert \"Bob\" F. Smith": 33, " Stephen Neal": 7, " Ronald V. Dellums": 57, " Mary Jo Kilroy": 23, " James H. Bilbray": 19, " Christopher Gibson": 9, " Thomas \"Tom\" Campbell": 71, " Adam Smith": 68, " Mark Foley": 286, " Alan B. Mollohan": 84, " Adrian Smith": 59, " Andrea Seastrand": 110, " Christopher \"Chris\" S. Murphy": 100, " Robert \"Bob\" K. Dornan": 169, " John M. Shimkus": 248, " Jeffrey \"Jeff\" M. Landry": 11, " Frank Riggs": 124, " Brian Higgins": 48, " James E. Rogan": 71, " Joe Heck": 14, " Alfred \"Al\" A. McCandless": 17, " Gregory Meeks": 92, " Mark Green": 82, " Norman Sisisky": 47, " Jon D. Fox": 180, " Ted Poe": 548, " Karen Lorraine \"Jackie\" Jacqueline Speier": 56, " Terry Everett": 71, " Todd Platts": 45, " Brad Ellsworth": 24, " Harold E. Sr. Ford": 23, " Donald Sherwood": 39, " Jay Inslee": 299, " Patrick Murphy": 30, " Julius \"J.C.\" Caesar Jr. Watts": 88, " Harold \"Hal\" Rogers": 159, " Michael Bilirakis": 140, " Julian Carey Dixon": 39, " Michael \"Mike\" Lynn Synar": 23, " Cathy McMorris": 7, " Mark S. Critz": 8, " Carlos Romero-Barcelo": 44, " Gary Franks": 30, " John E. Sununu": 30, " Nydia M. Velazquez": 205, " Stephen \"Steve\" Cohen": 195, " Brad Miller": 46, " Don Johnson": 8, " Enid Waldholtz": 36, " Earl Hutto": 22, " Hilda L. Solis": 174, " Carlos J. Moorhead": 46, " Gerry E. Studds": 55, " Thomas DeLay": 358, " David Emery": 1, " Billy Long": 8, " Patrick McHenry": 128, " R. \"Parker\" Griffith": 11, " Lynn Rivers": 53, " Dennis Ross": 5, " David B. McKinley": 10, " Randall \"Duke\" Cunningham": 361, " Michael N. Castle": 271, " Robert T. Matsui": 79, " James T. Walsh": 153, " Raymond \"Ray\" Jr. Thornton": 16, " Joe Knollenberg": 278, " Brian P. Bilbray": 157, " Jon Runyan": 6, " Mark Neumann": 95, " Chris Chocola": 36, " Susan Davis": 129, " Tom Graves": 17, " Unidentified Speaker": 8, " Mary Bono": 21, " Maria Cantwell": 15, " Matt Salmon": 56, " Sanford Jr. Bishop": 124, " W. \"Todd\" Akin": 125, " Juanita McDonald": 143, " John Boozman": 117, " Tim Walberg": 60, " Gerald B. H. Solomon": 319, " John J. LaFalce": 82, " Steven Kuykendall": 20, " James \"Jim\" Slattery": 8, " Kay Granger": 86, " John \"Jack\" F. Reed": 50, " Michael McCaul": 64, " Bernard \"Bernie\" Sanders": 255, " Nicholas Lampson": 167, " C.A. \"Dutch\" Ruppersberger": 38, " Jerrold Nadler": 352, " Maurice Hinchey": 234, " Thaddeus \"Thad\" McCotter": 100, " Rick White": 33, " James \"Jim\" A. Himes": 47, " Timothy J. Penny": 41, " Kendrick Meek": 123, " Jose Serrano": 110, " Harris W. Fawell": 52, " Gregorio \"Kilili\" Sablan": 31, " Peter Blute": 54, " John W. Bryant": 52, " Katherine \"Kathy\" Anne Castor": 80, " Paul Gillmor": 37, " David A. Curson": 2, " Dan Hamburg": 15, " Robert L. Ehrlich": 50, " Martha Roby": 16, " Jerry Moran": 140, " Daniel \"Dan\" Davi Rostenkowski": 12, " Thelma D. Drake": 70, " Jim Chapman": 14, " Ray LaHood": 120, " John Sullivan": 53, " William \"Bill\" Zeliff": 46, " Ronald \"Ron\" Lee Wyden": 34, " Max Burns": 44, " Henry B. Gonzalez": 75, " Steven \"Steve\" M.D. Kagen": 84, " Richard Pombo": 79, " John M. McHugh": 83, " Marion \"Robert\" Berry": 130, " Bob Stump": 65, " Rush Holt": 255, " Martin Olav Sabo": 102, " Richard L Hanna": 3, " Deborah \"Debbie\" L. Halvorson": 20, " Fred Heineman": 24, " Richard Burr": 82, " William D. Ford": 21, " Clarence \"Saxby\" Chambliss": 104, " Jerry Lewis": 256, " Luis Fortuno": 6, " Jeff Flake": 247, " Barbara Lee": 342, " Jan Meyers": 68, " Enid Greene": 11, " James Davis": 77, " Mike Pence": 423, " E. B. Johnson": 221, " Eligio \"Kika\" De la Garza": 67, " Stephanie Tubbs Jones": 188, " Edward \"Ed\" Whitfield": 112, " Charles Djou": 8, " Tim P. Johnson": 16, " Lamar S. Smith": 357, " David Vitter": 43, " Frank Jr. Pallone": 767, " Wayne Gilchrest": 190, " James McGovern": 401, " Karen McCarthy": 55, " Gene Green": 483, " J. Alex McMillan": 7, " Gerald \"Jerry\" D. Kleczka": 102, " Barbara B. Kennelly": 144, " Theodore \"Ted\" E. Deutch": 28, " Michael \"Mike\" Simpson": 43, " Tim Mahoney": 26, " Diane Lynn Black": 17, " Stephen \"Steve\" Horn": 219, " Artur Davis": 43, " Joseph M. III Hoeffel": 62, " Thomas \"Tom\" A. M.D. Coburn": 109, " Richard A. Gephardt": 241, " Karen Thurman": 121, " Patrick Tiberi": 30, " Christopher Van Hollen": 103, " Christopher Shays": 303, " Peter Hoagland": 15, " Devin Nunes": 32, " Robert \"Bob\" Nelson Clement": 92, " John Kline": 85, " M. Diaz-Balart": 71, " Sam Farr": 340, " Emanuel II Cleaver": 54, " Constance \"Connie\" A. Morella": 293, " Al Green": 90, " Michael Patrick Flanagan": 21, " Peter \"Pete\" King": 86, " Ronald D. Coleman": 43, " Donna M. Christensen": 195, " Bill Emerson": 67, " Brian Kerns": 7, " William \"Bill\" M.D. Cassidy": 26, " Barbara Rose Collins": 35, " John Adler": 5, " Bob Barr": 141, " Jo Ann Emerson": 77, " Ciro Rodriguez": 110, " Frederica Wilson": 9, " George W. Gekas": 216, " David Minge": 105, " David E. Skaggs": 175, " Charles \"Charlie\" Rose": 34, " Debbie Stabenow": 56, " Darrell Issa": 88, " Tom Barlow": 12, " Sonny Bono": 22, " John \"Johnny\" Isakson": 64, " Earl Pomeroy": 259, " Jay Johnson": 14, " Suellen \"Sue\" Myrick": 157, " Joseph \"Heath\" Shuler": 22, " J. Roy Rowland": 13, " Vernon J. Ehlers": 216, " Sam M. Gibbons": 67, " Paul Tonko": 90, " Gary Peters": 30, " Francisco \"Quico\" Canseco": 14, " Paul McHale": 27, " Marshall \"Mark\" Sanford": 85, " Samuel \"Sam\" B. Graves": 51, " Gerald \"Jerry\" McNerney": 55, " C. \"Christopher\" Cox": 172, " Steve \"Stephen\" Buyer": 201, " Dennis Kucinich": 460, " Hamilton \"Ham\" Jr. Fish": 26, " Ronald \"Ron\" Kind": 207, " Charlie \"Charles\" Melancon": 25, " Robert Wexler": 45, " Frank A. Cremeans": 7, " Marilyn Lloyd": 8, " Larry Combest": 57, " Henry Cuellar": 65, " David Schweikert": 9, " Major R. Owens": 255, " Marlin A. Stutzman": 14, " Ronnie Shows": 42, " Steve Pearce": 88, " Edward A. Pease": 27, " Joe Barton": 202, " Michael A. Andrews": 4, " Jeffrey \"Jeff\" Lane Fortenberry": 72, " F. \"James\" James Jr. Sensenbrenner": 213, " Craig Thomas": 79, " Wes Watkins": 31, " Mike Coffman": 42, " Ronald \"Ron\" M.D. Paul": 229, " David Scott": 102, " Jennifer Dunn": 167, " Louise Slaughter": 371, " Sheila Jackson Lee": 1048, " John Sweeney": 65, " John B. Larson": 107, " Steven \"Steve\" Austria": 14, " Carolyn Cheeks Kilpatrick": 137, " Kevin Brady": 161, " Robert \"Bob\" Goodlatte": 274, " Shelley Berkley": 196, " Harry E. Mitchell": 23, " Rodney Alexander": 10, " Scott McInnis": 156, " Benjamin \"Ben\" L. Cardin": 247, " John R. Thune": 116, " Neal Smith": 20, " Chaka Fattah": 127, " James \"Jim\" C. Greenwood": 77, " Vernon \"Vern\" Buchanan": 44, " John D. Jr. Dingell": 312, " Richard H. Baker": 54, " Robert \"Bobby\" Scott": 300, " Virgil H. Jr. Goode": 60, " Mo Brooks": 14, " Jason Altmire": 109, " Andre D. Carson": 27, " Ed Case": 20, " G. \"George\" K. Butterfield": 99, " Blaine Luetkemeyer": 15, " Sean P. Duffy": 9, " Eni Faleomavaega": 223, " Ron Klink": 120, " Richard \"Doc\" Hastings": 226, " Amory \"Amo\" Houghton": 88, " Rick Berg": 13, " John Yarmuth": 135, " Bill Foster": 11, " Christopher \"Chris\" H. Smith": 293, " Hansen Clarke": 23, " Chip Cravaack": 11, " Calvin Dooley": 68, " Edwin \"Ed\" G. Perlmutter": 103, " Chuck \"Charles\" J. Fleischmann": 8, " Rick Renzi": 39, " Peter Welch": 143, " William \"Bill\" Federici": 1, " Nick Joe Rahall": 157, " William J. Hughes": 34, " Ron Barber": 2, " Rob Bishop": 128, " Grace Napolitano": 46, " Andrew Walton": 2, " Kweisi Mfume": 38, " Mike Kreidler": 15, " Robert A. Brady": 27, " Bob Gibbs": 5, " Owen B. Pickett": 30, " Tillie Fowler": 112, " Thomas \"Tom\" Latham": 126, " Scott Rigell": 5, " John Culberson": 73, " Michael Huffington": 4, " Thomas \"Tom\" Tancredo": 150, " Ben Quayle": 12, " Sue Kelly": 160, " Carrie Meek": 195, " Harold Lee Volkmer": 149, " J.J. \"JJ\" Pickle": 20, " Thomas \"Tom\" Reynolds": 88, " Timothy \"Tim\" Walz": 81, " K. \"Mike\" Michael Conaway": 116, " Walter III Tucker": 42, " Clifford \"Cliff\" Stearns": 636, " Ronald Machtley": 12, " Greg Ganske": 141, " Nan Hayworth": 15, " Herbert \"Sonny\" Leon Callahan": 107, " Timothy V. Johnson": 7, " Betty Sutton": 97, " David \"Dave\" Lee Camp": 160, " Charles W. Jr. Boustany": 110, " Mazie Hirono": 61, " Sam Coppersmith": 19, " Marilyn Musgrave": 48, " Steven Palazzo": 22, " Michael \"Mike\" Thompson": 77, " Michael \"Mike\" Richard Pompeo": 19, " Frederick \"Fred\" S. Upton": 169, " Walter Holden Capps": 21, " Sidney Yates": 42, " Kevin W. Yoder": 17, " Frank Ballance": 8, " Tom Bevill": 28, " Thomas \"Tom\" S. Foley": 16, " James A. Jr. Traficant": 688, " David Wu": 108, " Phil MD Gingrey": 308, " Blanche Lambert Lincoln": 24, " H. Martin Lancaster": 12, " John \"Joe\" J.H. Schwarz": 12, " William J. Coyne": 17, " Michael Ward": 72, " Robert Andrews": 280, " Robert \"Bob\" R. Riley": 32, " Leonard L. Boswell": 93, " George Nethercutt": 111, " Thomas \"Tom\" W. II Reed": 14, " Michele M. Bachmann": 71, " David E. Bonior": 338, " Philip \"Phil\" M. Crane": 114, " Dale E. Kildee": 177, " John Mica": 343, " Vicky Hartzler": 15, " Nicola \"Niki\" S. Tsongas": 31, " Herbert H. Bateman": 54, " Bob Etheridge": 190, " James Bacchus": 11, " Douglas \"Doug\" K. Bereuter": 270, " Bill Johnson": 25}